dpeaDPi/DPiButton.py
dpeaDPi/DPiClockNBlock.py
dpeaDPi/DPiComputer.py
dpeaDPi/DPiDigitalIn.py
dpeaDPi/DPiFuncGen.py
dpeaDPi/DPiNetwork.py
dpeaDPi/DPiPowerDrive.py
dpeaDPi/DPiRobot.py
dpeaDPi/DPiSolenoid.py
dpeaDPi/DPiStepper.py
dpeaDPi/__init__.py
dpeaDPi-0.1.6.dist-info/LICENSE
dpeaDPi-0.1.6.dist-info/METADATA
dpeaDPi-0.1.6.dist-info/WHEEL
dpeaDPi-0.1.6.dist-info/top_level.txt
dpeaDPi-0.1.6.dist-info/RECORD
