Metadata-Version: 2.1
Name: dpeaDPi
Version: 0.1.6
Summary: Python package infrastructure for DPEA's DPi boards
Author: Stan Reifel
License-File: LICENSE
Requires-Dist: pyserial
Requires-Dist: requests
Requires-Dist: smbus2
Requires-Dist: adafruit-blinka
Requires-Dist: adafruit-circuitpython-vl6180x
